hulk/__init__.py
hulk/basic/__init__.py
hulk/basic/hulk/__init__.py
hulk/basic/hulk/str/__init__.py
hulk/basic/hulk/str/strutilsex.py
hulk/basic/hulk_db_base/__init__.py
hulk/basic/hulk_io_base/__init__.py
hulk/basic/hulk_io_base/io/__init__.py
hulk/basic/hulk_io_base/io/file/__init__.py
hulk/basic/hulk_io_base/io/file/fileutilsex.py
hulk/basic/hulk_io_base/io/json/__init__.py
hulk/basic/hulk_io_base/io/json/jsonutilsex.py
hulk/basic/hulk_io_base/proc/__init__.py
hulk/basic/hulk_misc_base/__init__.py
hulk/basic/hulk_misc_base/log/__init__.py
hulk/basic/hulk_misc_base/log/logutilsex.py
hulk/basic/hulk_misc_netcard/__init__.py
hulk/basic/hulk_misc_usb/__init__.py
hulk/basic/hulk_net_base/__init__.py
hulk/basic/hulk_net_base/http/__init__.py
hulk/basic/hulk_net_base/http/httputilsex.py
hulk/basic/hulk_security_base/__init__.py
hulk/basic/hulk_security_base/obfuscator/__init__.py
hulk/basic/hulk_security_base/obfuscator/obfuscatorutilsex.py
hulk/basic/hulk_z/__init__.py
hulk/basic/hulk_z/log/__init__.py
hulk/basic/hulk_z/log/logutilsex2.py
hulk/cv/__init__.py
hulk/cv/yolov8/YOLOv8.py
hulk/cv/yolov8/__init__.py
hulk/cv/z_reference/__init__.py
hulk/cv/z_reference/image_object_detection.py
hulk/cv/z_reference/video_object_detection.py
hulk/cv/z_reference/webcam_object_detection.py
hulk/cv/z_reference/z_Server.py
hulk_ultimate_python-0.0.12.dist-info/LICENSE
hulk_ultimate_python-0.0.12.dist-info/METADATA
hulk_ultimate_python-0.0.12.dist-info/WHEEL
hulk_ultimate_python-0.0.12.dist-info/top_level.txt
hulk_ultimate_python-0.0.12.dist-info/RECORD
