Metadata-Version: 2.1
Name: hulk-ultimate-python
Version: 0.0.12
Summary: Hulk Library for Python.
Author-email: JHercules <JHercules_qz@qq.com>
Project-URL: Homepage, https://github.com/JHerculesqz/Hulk
Project-URL: Issues, https://github.com/JHerculesqz/Hulk/issues
Classifier: Programming Language :: Python :: 3
Classifier: License :: OSI Approved :: MIT License
Classifier: Operating System :: OS Independent
Requires-Python: >=3.9
License-File: LICENSE
